{
  "id": "dan-wolgamott",
  "name": "Dan Wolgamott",
  "firstName": "Dan",
  "lastName": "Wolgamott",
  "photo": "/images/officials/state-legislature/mn/dan-wolgamott.jpg",
  "photoSourceUrl": "https://www.house.mn.gov/hinfo/memberimgls94/14B.gif?v=112221",
  "photoCredit": "OpenStates public profile image source",
  "party": "D",
  "level": "state",
  "position": "State Representative",
  "district": "HD-14B",
  "jurisdiction": "Minnesota House of Representatives",
  "county": [
    "Minnesota"
  ],
  "termStart": "2019-01-08",
  "termEnd": "Current public term pending source review",
  "contactInfo": {
    "office": "Centennial Office Building 658 Cedar St., Fifth Floor, St. Paul, MN 55155",
    "phone": "651-296-6612",
    "email": "rep.dan.wolgamott@house.mn.gov",
    "website": "https://www.house.mn.gov/members/profile/15499"
  },
  "bio": "Dan Wolgamott serves as State Representative for Minnesota House of Representatives District 14B. This RepWatchr starter profile is source-seeded from OpenStates public people data, official public links, and public profile photo sources where available.",
  "campaignPromises": [],
  "reviewStatus": "source_seeded",
  "state": "MN",
  "sourceLinks": [
    {
      "title": "Official public profile",
      "url": "https://www.house.mn.gov/members/profile/15499"
    },
    {
      "title": "OpenStates public people record",
      "url": "https://raw.githubusercontent.com/openstates/people/d13b1a42510bc019831d0b56f23186c2342acb11/data/mn/legislature/Dan-Wolgamott-57755948-5912-49c5-b8b7-65c110ae44d9.yml"
    },
    {
      "title": "Public profile photo source",
      "url": "https://www.house.mn.gov/hinfo/memberimgls94/14B.gif?v=112221"
    },
    {
      "title": "Public source",
      "url": "https://ballotpedia.org/Dan_Wolgamott"
    },
    {
      "title": "Public source",
      "url": "https://en.wikipedia.org/wiki/Dan_Wolgamott"
    },
    {
      "title": "Public source",
      "url": "https://justfacts.votesmart.org/candidate/biography/152827/dan-wolgamott"
    },
    {
      "title": "Public source",
      "url": "https://www.house.leg.state.mn.us/members/hmem.asp"
    }
  ],
  "lastVerifiedAt": "2026-05-01"
}
