{
  "id": "kasey-carpenter",
  "name": "Kasey Carpenter",
  "firstName": "Kasey",
  "lastName": "Carpenter",
  "party": "R",
  "level": "state",
  "position": "State Representative",
  "district": "HD-4",
  "jurisdiction": "Georgia House of Representatives",
  "county": [
    "Georgia"
  ],
  "termStart": "2017-11-20",
  "termEnd": "Current public term pending source review",
  "contactInfo": {
    "office": "State Capitol Room 401-I, 206 Washington St. SW, Atlanta, GA 30334",
    "phone": "404-656-7857",
    "email": "kasey.carpenter@house.ga.gov",
    "website": "https://www.house.ga.gov/Representatives/en-US/member.aspx?Member=4911&Session=27"
  },
  "bio": "Kasey Carpenter serves as State Representative for Georgia House of Representatives District 4. This RepWatchr starter profile is source-seeded from OpenStates public people data, official public links, and public profile photo sources where available.",
  "campaignPromises": [],
  "reviewStatus": "source_seeded",
  "state": "GA",
  "sourceLinks": [
    {
      "title": "Official public profile",
      "url": "https://www.house.ga.gov/Representatives/en-US/member.aspx?Member=4911&Session=27"
    },
    {
      "title": "OpenStates public people record",
      "url": "https://raw.githubusercontent.com/openstates/people/d13b1a42510bc019831d0b56f23186c2342acb11/data/ga/legislature/Kasey-Carpenter-97a40ea4-674f-4b84-8fd3-8bc2f3b4a35d.yml"
    },
    {
      "title": "Public source",
      "url": "https://ballotpedia.org/Kasey_Carpenter"
    },
    {
      "title": "Public source",
      "url": "https://en.wikipedia.org/wiki/Kasey_Carpenter"
    },
    {
      "title": "Public source",
      "url": "https://justfacts.votesmart.org/candidate/biography/168187/kasey-carpenter"
    },
    {
      "title": "Public source",
      "url": "https://webservices.legis.ga.gov/GGAServices/Members/Service.svc?wsdl"
    },
    {
      "title": "Detail page (requires authorization token)",
      "url": "https://www.legis.ga.gov/api/members/detail/4911?session=1029&chamber=1"
    },
    {
      "title": "API member detail (requires authorization token)",
      "url": "https://www.legis.ga.gov/api/members/detail/4911?session=1031&chamber=1"
    },
    {
      "title": "API members list (requires authorization token)",
      "url": "https://www.legis.ga.gov/api/members/list/1031"
    },
    {
      "title": "Public source",
      "url": "https://www.legis.ga.gov/members/house/4911"
    }
  ],
  "lastVerifiedAt": "2026-05-01"
}
