{
  "id": "bill-herbkersman",
  "name": "Bill Herbkersman",
  "firstName": "Bill",
  "lastName": "Herbkersman",
  "party": "R",
  "level": "state",
  "position": "State Representative",
  "district": "HD-118",
  "jurisdiction": "South Carolina House of Representatives",
  "county": [
    "South Carolina"
  ],
  "termStart": "2002-11-11",
  "termEnd": "Current public term pending source review",
  "contactInfo": {
    "office": "Room 407, Blatt Building P.O. Box 11867, Columbia, SC 29201",
    "phone": "803-734-3015",
    "email": "billherbkerman@schouse.gov",
    "website": "https://repbillherbkersman.com/"
  },
  "bio": "Bill Herbkersman serves as State Representative for South Carolina House of Representatives District 118. This RepWatchr starter profile is source-seeded from OpenStates public people data, official public links, and public profile photo sources where available.",
  "campaignPromises": [],
  "reviewStatus": "source_seeded",
  "state": "SC",
  "sourceLinks": [
    {
      "title": "Official public profile",
      "url": "https://repbillherbkersman.com/"
    },
    {
      "title": "OpenStates public people record",
      "url": "https://raw.githubusercontent.com/openstates/people/d13b1a42510bc019831d0b56f23186c2342acb11/data/sc/legislature/William-G-Bill-Herbkersman-e27051a1-60e8-4ad9-b1d2-55360e09ea8c.yml"
    },
    {
      "title": "Public source",
      "url": "https://ballotpedia.org/Bill_Herbkersman"
    },
    {
      "title": "Public source",
      "url": "https://en.wikipedia.org/wiki/Bill_Herbkersman"
    },
    {
      "title": "Public source",
      "url": "https://justfacts.votesmart.org/candidate/47897/bill-herbkersman"
    },
    {
      "title": "Public source",
      "url": "https://repbillherbkersman.com"
    },
    {
      "title": "Public source",
      "url": "https://repbillherbkersman.com/about-bill"
    },
    {
      "title": "Public source",
      "url": "https://scstatehouse.gov/member.php?chamber=H"
    },
    {
      "title": "Public source",
      "url": "https://scstatehouse.gov/member.php?code=0832954446"
    },
    {
      "title": "Public source",
      "url": "https://www.linkedin.com/in/bill-herbkersman-0575507"
    }
  ],
  "lastVerifiedAt": "2026-05-01"
}
