{
  "id": "nacogdoches-isd-board-2",
  "name": "Victoria Payne",
  "firstName": "Victoria",
  "lastName": "Payne",
  "party": "NP",
  "level": "school-board",
  "position": "School Board Vice President",
  "district": "Place 2",
  "jurisdiction": "Nacogdoches ISD",
  "county": ["Nacogdoches"],
  "termStart": "2024-05-01",
  "termEnd": "2028-05-01",
  "contactInfo": {
    "office": "2507 North St., Nacogdoches, TX 75965",
    "phone": "(936) 569-5000",
    "website": "https://www.nacisd.org/board"
  },
  "bio": "Victoria Payne serves as Vice President of the Nacogdoches ISD Board of Trustees. She advocates for equitable resources and expanded dual-credit programs for Nacogdoches high school students."
}
