{
  "id": "susan-porcelli",
  "name": "Susan Porcelli",
  "firstName": "Susan",
  "lastName": "Porcelli",
  "photo": "/images/officials/state-legislature/nh/susan-porcelli.jpg",
  "photoSourceUrl": "https://storage.googleapis.com/enview-dev-public-general/legislative-people-photos/123394.jpg",
  "photoCredit": "OpenStates public profile image source",
  "party": "R",
  "level": "state",
  "position": "State Representative",
  "district": "HD-Rockingham 19",
  "jurisdiction": "New Hampshire House of Representatives",
  "county": [
    "New Hampshire"
  ],
  "termStart": "2022-12-07",
  "termEnd": "Current public term pending source review",
  "contactInfo": {
    "office": "State House 107 N. Main St., Concord, NH 03301",
    "phone": "603-271-3661",
    "email": "susan.porcelli@gc.nh.gov",
    "website": "https://gc.nh.gov/house/members/member.aspx?pid=10700"
  },
  "bio": "Susan Porcelli serves as State Representative for New Hampshire House of Representatives District Rockingham 19. This RepWatchr starter profile is source-seeded from OpenStates public people data, official public links, and public profile photo sources where available.",
  "campaignPromises": [],
  "reviewStatus": "source_seeded",
  "state": "NH",
  "sourceLinks": [
    {
      "title": "Official public profile",
      "url": "https://gc.nh.gov/house/members/member.aspx?pid=10700"
    },
    {
      "title": "OpenStates public people record",
      "url": "https://raw.githubusercontent.com/openstates/people/d13b1a42510bc019831d0b56f23186c2342acb11/data/nh/legislature/Susan-M-Porcelli-64a835c6-0e89-411f-bc32-331e246b10f0.yml"
    },
    {
      "title": "Public profile photo source",
      "url": "https://storage.googleapis.com/enview-dev-public-general/legislative-people-photos/123394.jpg"
    },
    {
      "title": "Public source",
      "url": "https://ballotpedia.org/Susan_Porcelli"
    },
    {
      "title": "Public source",
      "url": "https://en.wikipedia.org/wiki/Susan_Porcelli"
    },
    {
      "title": "Public source",
      "url": "https://justfacts.votesmart.org/candidate/209239/susan-porcelli"
    },
    {
      "title": "Public source",
      "url": "https://www.gencourt.state.nh.us/house/members/member.aspx?pid=10700"
    },
    {
      "title": "Public source",
      "url": "https://www.linkedin.com/in/susan-m-porcelli-88925b203"
    }
  ],
  "lastVerifiedAt": "2026-05-01"
}
