{
  "id": "jay-richardson",
  "name": "Jay Richardson",
  "firstName": "Jay",
  "lastName": "Richardson",
  "photo": "/images/officials/state-legislature/ar/jay-richardson.jpg",
  "photoSourceUrl": "https://www.arkleg.state.ar.us/Content/photos/2023/House/562_sm.jpg",
  "photoCredit": "OpenStates public profile image source",
  "party": "D",
  "level": "state",
  "position": "State Representative",
  "district": "HD-49",
  "jurisdiction": "Arkansas House of Representatives",
  "county": [
    "Arkansas"
  ],
  "termStart": "2023-01-09",
  "termEnd": "Current public term pending source review",
  "contactInfo": {
    "office": "State Capitol Arkansas  500 Woodlane St., Suite 350, Little Rock, AR 72201",
    "phone": "501-682-6211",
    "email": "jay.richardson@arkansashouse.org",
    "website": "https://arkleg.state.ar.us/Legislators/Detail?member=J.+Richardson"
  },
  "bio": "Jay Richardson serves as State Representative for Arkansas House of Representatives District 49. This RepWatchr starter profile is source-seeded from OpenStates public people data, official public links, and public profile photo sources where available.",
  "campaignPromises": [],
  "reviewStatus": "source_seeded",
  "state": "AR",
  "sourceLinks": [
    {
      "title": "Official public profile",
      "url": "https://arkleg.state.ar.us/Legislators/Detail?member=J.+Richardson"
    },
    {
      "title": "OpenStates public people record",
      "url": "https://raw.githubusercontent.com/openstates/people/d13b1a42510bc019831d0b56f23186c2342acb11/data/ar/legislature/Jay-Richardson-65961429-87cb-4c8c-b9c9-006622ea63c7.yml"
    },
    {
      "title": "Public profile photo source",
      "url": "https://www.arkleg.state.ar.us/Content/photos/2023/House/562_sm.jpg"
    },
    {
      "title": "Public source",
      "url": "https://ballotpedia.org/Jay_Richardson"
    },
    {
      "title": "Public source",
      "url": "https://en.wikipedia.org/wiki/Jay_Richardson_(politician)"
    },
    {
      "title": "Public source",
      "url": "https://justfacts.votesmart.org/candidate/biography/178580/jay-richardson"
    },
    {
      "title": "Public source",
      "url": "https://www.arkansashouse.org/district/49"
    },
    {
      "title": "Public source",
      "url": "https://www.arkleg.state.ar.us/Legislators/Detail?member=J.+Richardson&ddBienniumSession=2023%2F2023R"
    },
    {
      "title": "Public source",
      "url": "https://www.arkleg.state.ar.us/Legislators/List?sort=Type&by=desc&ddBienniumSession=2023%2F2023R#SearchResults"
    }
  ],
  "lastVerifiedAt": "2026-05-01"
}
