{
  "id": "mike-bost",
  "name": "Mike Bost",
  "firstName": "Mike",
  "lastName": "Bost",
  "photo": "/images/officials/federal/mike-bost.jpg",
  "photoSourceUrl": "https://unitedstates.github.io/images/congress/225x275/B001295.jpg",
  "photoCredit": "UnitedStates project congressional image mirror",
  "party": "R",
  "level": "federal",
  "position": "U.S. Representative",
  "district": "IL-12",
  "jurisdiction": "U.S. House of Representatives",
  "county": [],
  "termStart": "2025-01-03",
  "termEnd": "2027-01-03",
  "contactInfo": {
    "office": "352 Cannon House Office Building",
    "phone": "202-225-5661",
    "email": "https://bost.house.gov",
    "website": "https://bost.house.gov"
  },
  "bio": "Mike Bost serves as the U.S. Representative for Illinois's 12th Congressional District. This RepWatchr starter profile is source-seeded from current congressional roster data, official public links, and public congressional photo sources.",
  "campaignPromises": [],
  "reviewStatus": "source_seeded",
  "state": "IL",
  "bioguideId": "B001295",
  "sourceLinks": [
    {
      "title": "Official congressional website",
      "url": "https://bost.house.gov"
    },
    {
      "title": "Congress legislators current roster",
      "url": "https://raw.githubusercontent.com/unitedstates/congress-legislators/master/legislators-current.yaml"
    },
    {
      "title": "Biographical Directory of the United States Congress",
      "url": "https://bioguide.congress.gov/search/bio/B001295"
    },
    {
      "title": "Congressional photo source",
      "url": "https://unitedstates.github.io/images/congress/225x275/B001295.jpg"
    }
  ],
  "lastVerifiedAt": "2026-04-29"
}
